FlexATA/__init__.py
FlexATA/form_builder.py
FlexATA/utility.py
FlexATA/data/sample_enemy_pairs_for_ATA.xlsx
FlexATA/data/sample_items_for_ATA.xlsx
flexata-0.0.12.dist-info/METADATA
flexata-0.0.12.dist-info/WHEEL
flexata-0.0.12.dist-info/licenses/LICENSE
flexata-0.0.12.dist-info/RECORD
