Metadata-Version: 2.4
Name: FlexATA
Version: 0.0.12
Summary: A flexible mixed integer program for automated test assembly (ATA) in Python.
Project-URL: Homepage, https://github.com/frankyanfu/FlexATA
Project-URL: Issues, https://github.com/frankyanfu/FlexATA/issues
Author-email: Yan Fu <yanfu.phd@gmail.com>
License-Expression: MIT
License-File: LICENSE
Classifier: Operating System :: OS Independent
Classifier: Programming Language :: Python :: 3
Requires-Python: >=3.10
Requires-Dist: cplex>=22.1
Requires-Dist: numpy>=2.2
Requires-Dist: openpyxl>=3.1
Requires-Dist: pandas>=2.2
Requires-Dist: pulp>=3.1
